ward_metrics-0.9.5.dist-info/DESCRIPTION.rst
ward_metrics-0.9.5.dist-info/METADATA
ward_metrics-0.9.5.dist-info/RECORD
ward_metrics-0.9.5.dist-info/WHEEL
ward_metrics-0.9.5.dist-info/metadata.json
ward_metrics-0.9.5.dist-info/top_level.txt
wardmetrics/__init__.py
wardmetrics/core_methods.py
wardmetrics/utils.py
wardmetrics/version.py
wardmetrics/visualisations.py
