Metadata-Version: 2.0
Name: ward-metrics
Version: 0.9.5
Summary: Tools for event-based evaluation for activity recognition problems.
Home-page: https://github.com/phev8/ward-metrics/
Author: Peter Hevesi
Author-email: peter.hevesi.developer@gmail.com
License: MIT
Keywords: machine learning,activity recognition,evaluation
Platform: UNKNOWN
Classifier: Development Status :: 3 - Alpha
Classifier: Intended Audience :: Science/Research
Classifier: Topic :: Scientific/Engineering
Classifier: License :: OSI Approved :: MIT License
Classifier: Programming Language :: Python :: 3 :: Only
Requires-Dist: matplotlib
